README.md
setup.py
img2html/__init__.py
img2html/converter.py
img2html.egg-info/PKG-INFO
img2html.egg-info/SOURCES.txt
img2html.egg-info/dependency_links.txt
img2html.egg-info/entry_points.txt
img2html.egg-info/requires.txt
img2html.egg-info/top_level.txt