Metadata-Version: 1.0
Name: img2html
Version: 0.0.7
Summary: Convert image to HTML
Home-page: https://github.com/xlzd/img2html
Author: xlzd
Author-email: i@xlzd.me
License: WTFPL
Platform: UNKNOWN
